{
  "updatedAt": "2025-11-27T23:45:04.152Z",
  "rows": [
    {
      "shortSymbol": "KOGE",
      "chainId": "56",
      "fourX": false,
      "change5m": 0.0000037373271026915385,
      "volatility5m": 0.000005129971009044327,
      "stability": "稳定",
      "quoteVolume24h": 148213264.0390809,
      "pair": "ALPHA_22USDT",
      "listedDays": 224
    },
    {
      "shortSymbol": "TIMI",
      "chainId": "56",
      "fourX": true,
      "change5m": 3.0000002998087414e-7,
      "volatility5m": 0.00008730000872998549,
      "stability": "稳定",
      "quoteVolume24h": 4168022319.3132024,
      "pair": "ALPHA_465USDT",
      "listedDays": 18
    },
    {
      "shortSymbol": "BSU",
      "chainId": "56",
      "fourX": false,
      "change5m": 0.0001471351681220023,
      "volatility5m": 0.0004897161959311004,
      "stability": "稳定",
      "quoteVolume24h": 88035506.22240852,
      "pair": "ALPHA_315USDT",
      "listedDays": 110
    },
    {
      "shortSymbol": "BAY",
      "chainId": "56",
      "fourX": true,
      "change5m": 0.000013589520841928314,
      "volatility5m": 0.002868908222959938,
      "stability": "稳定",
      "quoteVolume24h": 294369258.3375249,
      "pair": "ALPHA_452USDT",
      "listedDays": 26
    }
  ]
}