{
  "updatedAt": "2025-11-09T14:22:03.862Z",
  "rows": [
    {
      "shortSymbol": "KOGE",
      "chainId": "56",
      "fourX": false,
      "change5m": -8.332863994276727e-10,
      "volatility5m": 1.666572957238258e-7,
      "stability": "稳定",
      "quoteVolume24h": 327461923.513873,
      "pair": "ALPHA_22USDT",
      "listedDays": 206
    },
    {
      "shortSymbol": "ANOME",
      "chainId": "56",
      "fourX": true,
      "change5m": 0.000001347122138757199,
      "volatility5m": 0.0000024416588765120286,
      "stability": "稳定",
      "quoteVolume24h": 702552268.3758036,
      "pair": "ALPHA_433USDT",
      "listedDays": 23
    },
    {
      "shortSymbol": "MERL",
      "chainId": "56",
      "fourX": false,
      "change5m": -0.000002988691357402946,
      "volatility5m": 0.0000030156165047521247,
      "stability": "稳定",
      "quoteVolume24h": 368089888.86749566,
      "pair": "ALPHA_195USDT",
      "listedDays": 173
    },
    {
      "shortSymbol": "BANK",
      "chainId": "56",
      "fourX": false,
      "change5m": 0.00017004392801490723,
      "volatility5m": 0.0004676208020404049,
      "stability": "稳定",
      "quoteVolume24h": 631844335.2985656,
      "pair": "ALPHA_146USDT",
      "listedDays": 205
    },
    {
      "shortSymbol": "BEAT",
      "chainId": "56",
      "fourX": true,
      "change5m": 0.001003343769301181,
      "volatility5m": 0.0010672374502162024,
      "stability": "稳定",
      "quoteVolume24h": 844428811.1349734,
      "pair": "ALPHA_451USDT",
      "listedDays": 8
    },
    {
      "shortSymbol": "EVAA",
      "chainId": "56",
      "fourX": false,
      "change5m": -0.0005600814663950503,
      "volatility5m": 0.0021889002036659016,
      "stability": "稳定",
      "quoteVolume24h": 328717861.5513717,
      "pair": "ALPHA_409USDT",
      "listedDays": 37
    },
    {
      "shortSymbol": "AIO",
      "chainId": "56",
      "fourX": false,
      "change5m": -0.0024401464964817522,
      "volatility5m": 0.0024981028656194666,
      "stability": "稳定",
      "quoteVolume24h": 1214718485.9300148,
      "pair": "ALPHA_361USDT",
      "listedDays": 62
    },
    {
      "shortSymbol": "CDL",
      "chainId": "56",
      "fourX": true,
      "change5m": -0.0024772914946324916,
      "volatility5m": 0.0034530140379851423,
      "stability": "稳定",
      "quoteVolume24h": 2187328048.102154,
      "pair": "ALPHA_423USDT",
      "listedDays": 29
    },
    {
      "shortSymbol": "NB",
      "chainId": "56",
      "fourX": true,
      "change5m": -0.003030097420032705,
      "volatility5m": 0.00352384026622231,
      "stability": "稳定",
      "quoteVolume24h": 120039287.98990951,
      "pair": "ALPHA_450USDT",
      "listedDays": 9
    },
    {
      "shortSymbol": "BAY",
      "chainId": "56",
      "fourX": true,
      "change5m": 0.0022491752108228114,
      "volatility5m": 0.004044889662120139,
      "stability": "稳定",
      "quoteVolume24h": 167664284.32592943,
      "pair": "ALPHA_452USDT",
      "listedDays": 8
    },
    {
      "shortSymbol": "KLINK",
      "chainId": "56",
      "fourX": false,
      "change5m": 0.006559517566859009,
      "volatility5m": 0.012068694284215963,
      "stability": "稳定",
      "quoteVolume24h": 79431701.6634347,
      "pair": "ALPHA_415USDT",
      "listedDays": 33
    }
  ]
}