{
  "updatedAt": "2025-10-02T01:46:33.660Z",
  "rows": [
    {
      "shortSymbol": "KOGE",
      "chainId": "56",
      "fourX": false,
      "change5m": 0,
      "volatility5m": 2.0832364169099035e-10,
      "stability": "稳定",
      "quoteVolume24h": 461324086.5233515,
      "pair": "ALPHA_22USDT",
      "listedDays": 168
    },
    {
      "shortSymbol": "ALEO",
      "chainId": "56",
      "fourX": true,
      "change5m": 4.677250774823244e-7,
      "volatility5m": 0.000008121408163706929,
      "stability": "稳定",
      "quoteVolume24h": 3173789558.4226274,
      "pair": "ALPHA_373USDT",
      "listedDays": 18
    },
    {
      "shortSymbol": "NUMI",
      "chainId": "56",
      "fourX": true,
      "change5m": -0.0008521739130434947,
      "volatility5m": 0.0011018027571579015,
      "stability": "稳定",
      "quoteVolume24h": 1356346004.912632,
      "pair": "ALPHA_387USDT",
      "listedDays": 11
    },
    {
      "shortSymbol": "MCH",
      "chainId": "56",
      "fourX": true,
      "change5m": -0.0006615214994486287,
      "volatility5m": 0.0017452223447261192,
      "stability": "稳定",
      "quoteVolume24h": 445094243.3675992,
      "pair": "ALPHA_351USDT",
      "listedDays": 29
    },
    {
      "shortSymbol": "POP",
      "chainId": "56",
      "fourX": true,
      "change5m": 0.0007926318629221584,
      "volatility5m": 0.0018937047279348588,
      "stability": "稳定",
      "quoteVolume24h": 262192404.9023806,
      "pair": "ALPHA_366USDT",
      "listedDays": 22
    },
    {
      "shortSymbol": "ZEUS",
      "chainId": "56",
      "fourX": true,
      "change5m": -0.0023863860609953584,
      "volatility5m": 0.0023863860609953584,
      "stability": "稳定",
      "quoteVolume24h": 165855156.62202057,
      "pair": "ALPHA_372USDT",
      "listedDays": 19
    },
    {
      "shortSymbol": "AOP",
      "chainId": "56",
      "fourX": true,
      "change5m": -0.0024334010446895164,
      "volatility5m": 0.002466627974462995,
      "stability": "稳定",
      "quoteVolume24h": 666043375.7421936,
      "pair": "ALPHA_382USDT",
      "listedDays": 13
    },
    {
      "shortSymbol": "Q",
      "chainId": "56",
      "fourX": true,
      "change5m": 0.0020812776723592497,
      "volatility5m": 0.0025645161290322243,
      "stability": "稳定",
      "quoteVolume24h": 315485154.47936606,
      "pair": "ALPHA_349USDT",
      "listedDays": 30
    },
    {
      "shortSymbol": "BOT",
      "chainId": "56",
      "fourX": true,
      "change5m": -0.0031390557457345804,
      "volatility5m": 0.0036204513567706146,
      "stability": "稳定",
      "quoteVolume24h": 209509450.14266402,
      "pair": "ALPHA_353USDT",
      "listedDays": 29
    },
    {
      "shortSymbol": "FROGGIE",
      "chainId": "56",
      "fourX": true,
      "change5m": 0.005022321428571612,
      "volatility5m": 0.005022321428571612,
      "stability": "稳定",
      "quoteVolume24h": 684462796.9971995,
      "pair": "ALPHA_386USDT",
      "listedDays": 12
    }
  ]
}