{
  "updatedAt": "2026-01-28T19:23:36.972Z",
  "rows": [
    {
      "shortSymbol": "STAR",
      "chainId": "56",
      "fourX": false,
      "change5m": -0.0000183333455156168,
      "volatility5m": 0.000019411777604702255,
      "stability": "稳定",
      "quoteVolume24h": 53834398.28665639,
      "pair": "ALPHA_359USDT",
      "listedDays": 144
    },
    {
      "shortSymbol": "MGO",
      "chainId": "56",
      "fourX": false,
      "change5m": 0.0009733388230365744,
      "volatility5m": 0.001371342304664144,
      "stability": "稳定",
      "quoteVolume24h": 227205252.5306226,
      "pair": "ALPHA_242USDT",
      "listedDays": 218
    },
    {
      "shortSymbol": "ESPORTS",
      "chainId": "56",
      "fourX": false,
      "change5m": -0.0002919403248399592,
      "volatility5m": 0.002140229230268156,
      "stability": "稳定",
      "quoteVolume24h": 53464741.52320821,
      "pair": "ALPHA_283USDT",
      "listedDays": 193
    },
    {
      "shortSymbol": "OWL",
      "chainId": "56",
      "fourX": true,
      "change5m": -0.000663358369745818,
      "volatility5m": 0.0025821062435005425,
      "stability": "稳定",
      "quoteVolume24h": 2175214485.028112,
      "pair": "ALPHA_556USDT",
      "listedDays": 13
    },
    {
      "shortSymbol": "GWEI",
      "chainId": "56",
      "fourX": true,
      "change5m": 0.0022593693358713965,
      "volatility5m": 0.004166577139217513,
      "stability": "稳定",
      "quoteVolume24h": 82054802.7714261,
      "pair": "ALPHA_588USDT",
      "listedDays": 7
    },
    {
      "shortSymbol": "FIGHT",
      "chainId": "56",
      "fourX": true,
      "change5m": -0.005076476049783682,
      "volatility5m": 0.0064780984171018486,
      "stability": "稳定",
      "quoteVolume24h": 286958514.2489414,
      "pair": "ALPHA_604USDT",
      "listedDays": 6
    },
    {
      "shortSymbol": "TIMI",
      "chainId": "56",
      "fourX": false,
      "change5m": 0.058565036141813596,
      "volatility5m": 0.152981221555054,
      "stability": "较差",
      "quoteVolume24h": 53861793.18218608,
      "pair": "ALPHA_465USDT",
      "listedDays": 80
    }
  ]
}