{
  "updatedAt": "2026-02-28T23:50:45.522Z",
  "rows": [
    {
      "shortSymbol": "STABLE",
      "chainId": "56",
      "fourX": false,
      "change5m": -0.000011677243514065629,
      "volatility5m": 0.0007921589519011222,
      "stability": "稳定",
      "quoteVolume24h": 1579972000.024464,
      "pair": "ALPHA_488USDT",
      "listedDays": 82
    },
    {
      "shortSymbol": "JCT",
      "chainId": "56",
      "fourX": false,
      "change5m": -0.000947587730307698,
      "volatility5m": 0.00146844721120537,
      "stability": "稳定",
      "quoteVolume24h": 57163572.81968122,
      "pair": "ALPHA_466USDT",
      "listedDays": 110
    },
    {
      "shortSymbol": "GUA",
      "chainId": "56",
      "fourX": false,
      "change5m": 0.0018201826484017737,
      "volatility5m": 0.002164337899543413,
      "stability": "稳定",
      "quoteVolume24h": 158609601.87080058,
      "pair": "ALPHA_483USDT",
      "listedDays": 93
    }
  ]
}