{
  "updatedAt": "2025-12-10T21:59:02.801Z",
  "rows": [
    {
      "shortSymbol": "KOGE",
      "chainId": "56",
      "fourX": false,
      "change5m": 2.9374999889513707e-8,
      "volatility5m": 2.9374999889513707e-8,
      "stability": "稳定",
      "quoteVolume24h": 56674000.74243792,
      "pair": "ALPHA_22USDT",
      "listedDays": 237
    },
    {
      "shortSymbol": "ARTX",
      "chainId": "56",
      "fourX": true,
      "change5m": -0.0003401595214356341,
      "volatility5m": 0.0010787437686938454,
      "stability": "稳定",
      "quoteVolume24h": 2799588067.3025513,
      "pair": "ALPHA_474USDT",
      "listedDays": 19
    },
    {
      "shortSymbol": "ESPORTS",
      "chainId": "56",
      "fourX": false,
      "change5m": -0.0014608237843504776,
      "volatility5m": 0.0016990744456937496,
      "stability": "稳定",
      "quoteVolume24h": 94110075.33892287,
      "pair": "ALPHA_283USDT",
      "listedDays": 144
    },
    {
      "shortSymbol": "JCT",
      "chainId": "56",
      "fourX": true,
      "change5m": 0.0020060358601100858,
      "volatility5m": 0.0033641043848748834,
      "stability": "稳定",
      "quoteVolume24h": 375358554.4504358,
      "pair": "ALPHA_466USDT",
      "listedDays": 30
    },
    {
      "shortSymbol": "DGRAM",
      "chainId": "56",
      "fourX": true,
      "change5m": 0.002879290000959803,
      "volatility5m": 0.005905367335301731,
      "stability": "稳定",
      "quoteVolume24h": 441108021.0958757,
      "pair": "ALPHA_471USDT",
      "listedDays": 22
    },
    {
      "shortSymbol": "LAB",
      "chainId": "56",
      "fourX": false,
      "change5m": -0.009442722367416929,
      "volatility5m": 0.010231163516278615,
      "stability": "稳定",
      "quoteVolume24h": 129913037.41038778,
      "pair": "ALPHA_428USDT",
      "listedDays": 57
    }
  ]
}