{
  "updatedAt": "2025-12-10T10:51:37.357Z",
  "rows": [
    {
      "shortSymbol": "KOGE",
      "chainId": "56",
      "fourX": false,
      "change5m": 0.000004045372164281011,
      "volatility5m": 0.0003833089598566359,
      "stability": "稳定",
      "quoteVolume24h": 59528082.53158927,
      "pair": "ALPHA_22USDT",
      "listedDays": 237
    },
    {
      "shortSymbol": "ARTX",
      "chainId": "56",
      "fourX": true,
      "change5m": 0.0006247121873758035,
      "volatility5m": 0.0006247121873758035,
      "stability": "稳定",
      "quoteVolume24h": 2981759795.70523,
      "pair": "ALPHA_474USDT",
      "listedDays": 19
    },
    {
      "shortSymbol": "ESPORTS",
      "chainId": "56",
      "fourX": false,
      "change5m": 0.000406024427057314,
      "volatility5m": 0.000935589275668864,
      "stability": "稳定",
      "quoteVolume24h": 132626485.84477822,
      "pair": "ALPHA_283USDT",
      "listedDays": 144
    },
    {
      "shortSymbol": "LAB",
      "chainId": "56",
      "fourX": false,
      "change5m": 0.0014168089606919406,
      "volatility5m": 0.002953593171354801,
      "stability": "稳定",
      "quoteVolume24h": 71147473.42813934,
      "pair": "ALPHA_428USDT",
      "listedDays": 57
    },
    {
      "shortSymbol": "DGRAM",
      "chainId": "56",
      "fourX": true,
      "change5m": 0.000512958073913038,
      "volatility5m": 0.003280108050618251,
      "stability": "稳定",
      "quoteVolume24h": 417685131.03308547,
      "pair": "ALPHA_471USDT",
      "listedDays": 22
    },
    {
      "shortSymbol": "TIMI",
      "chainId": "56",
      "fourX": false,
      "change5m": -0.00023723854335544386,
      "volatility5m": 0.003311652366454385,
      "stability": "稳定",
      "quoteVolume24h": 52670760.9104306,
      "pair": "ALPHA_465USDT",
      "listedDays": 31
    },
    {
      "shortSymbol": "GAIX",
      "chainId": "56",
      "fourX": true,
      "change5m": 0,
      "volatility5m": 0.003580504869671427,
      "stability": "稳定",
      "quoteVolume24h": 60204430.43201044,
      "pair": "ALPHA_485USDT",
      "listedDays": 11
    },
    {
      "shortSymbol": "JCT",
      "chainId": "56",
      "fourX": true,
      "change5m": -0.002385074573031183,
      "volatility5m": 0.006916265397031493,
      "stability": "稳定",
      "quoteVolume24h": 710076612.3549801,
      "pair": "ALPHA_466USDT",
      "listedDays": 30
    }
  ]
}