{
  "updatedAt": "2025-12-25T22:16:03.509Z",
  "rows": [
    {
      "shortSymbol": "KOGE",
      "chainId": "56",
      "fourX": false,
      "change5m": 1.3290761124377199e-7,
      "volatility5m": 0.000013115564723512393,
      "stability": "稳定",
      "quoteVolume24h": 52361963.55541312,
      "pair": "ALPHA_22USDT",
      "listedDays": 252
    },
    {
      "shortSymbol": "ESPORTS",
      "chainId": "56",
      "fourX": false,
      "change5m": -0.00028486746987952343,
      "volatility5m": 0.0009328433734938742,
      "stability": "稳定",
      "quoteVolume24h": 1058567100.8384126,
      "pair": "ALPHA_283USDT",
      "listedDays": 159
    },
    {
      "shortSymbol": "LISA",
      "chainId": "56",
      "fourX": true,
      "change5m": 0.0005704506560181916,
      "volatility5m": 0.000961152310325119,
      "stability": "稳定",
      "quoteVolume24h": 817054602.7556746,
      "pair": "ALPHA_501USDT",
      "listedDays": 7
    },
    {
      "shortSymbol": "RLS",
      "chainId": "56",
      "fourX": true,
      "change5m": -0.0007250481151979943,
      "volatility5m": 0.0016137704583811662,
      "stability": "稳定",
      "quoteVolume24h": 1222341118.2182903,
      "pair": "ALPHA_486USDT",
      "listedDays": 24
    },
    {
      "shortSymbol": "NIGHT",
      "chainId": "56",
      "fourX": true,
      "change5m": -0.0014319013066412243,
      "volatility5m": 0.001982217842092126,
      "stability": "稳定",
      "quoteVolume24h": 2076812826.984077,
      "pair": "ALPHA_489USDT",
      "listedDays": 16
    },
    {
      "shortSymbol": "STABLE",
      "chainId": "56",
      "fourX": true,
      "change5m": -0.006443480352418257,
      "volatility5m": 0.006443480352418257,
      "stability": "稳定",
      "quoteVolume24h": 265720455.60438192,
      "pair": "ALPHA_488USDT",
      "listedDays": 17
    }
  ]
}