{
  "updatedAt": "2025-11-28T06:46:10.349Z",
  "rows": [
    {
      "shortSymbol": "TIMI",
      "chainId": "56",
      "fourX": true,
      "change5m": 0,
      "volatility5m": 2.0000002003350871e-7,
      "stability": "稳定",
      "quoteVolume24h": 4182049516.429908,
      "pair": "ALPHA_465USDT",
      "listedDays": 19
    },
    {
      "shortSymbol": "KOGE",
      "chainId": "56",
      "fourX": false,
      "change5m": 5.045615451094382e-7,
      "volatility5m": 0.0000041871108566725515,
      "stability": "稳定",
      "quoteVolume24h": 147696206.44860205,
      "pair": "ALPHA_22USDT",
      "listedDays": 225
    },
    {
      "shortSymbol": "BSU",
      "chainId": "56",
      "fourX": false,
      "change5m": -0.00009686354824410257,
      "volatility5m": 0.0018386965799417516,
      "stability": "稳定",
      "quoteVolume24h": 93546275.95384426,
      "pair": "ALPHA_315USDT",
      "listedDays": 111
    },
    {
      "shortSymbol": "BAY",
      "chainId": "56",
      "fourX": true,
      "change5m": 0.0014655834554652433,
      "volatility5m": 0.002222250185187487,
      "stability": "稳定",
      "quoteVolume24h": 367219907.0844545,
      "pair": "ALPHA_452USDT",
      "listedDays": 27
    }
  ]
}