{
  "updatedAt": "2026-04-12T21:48:58.604Z",
  "rows": [
    {
      "shortSymbol": "EDGE",
      "chainId": "56",
      "fourX": true,
      "change5m": 0.00029787802732315194,
      "volatility5m": 0.001851982914465478,
      "stability": "稳定",
      "quoteVolume24h": 264494833.43159133,
      "pair": "ALPHA_838USDT",
      "listedDays": 12
    },
    {
      "shortSymbol": "PRL",
      "chainId": "56",
      "fourX": true,
      "change5m": -0.0039801431453255825,
      "volatility5m": 0.00485681455096446,
      "stability": "稳定",
      "quoteVolume24h": 1032084029.6798364,
      "pair": "ALPHA_823USDT",
      "listedDays": 18
    }
  ]
}