{
  "updatedAt": "2025-10-08T19:57:53.496Z",
  "rows": [
    {
      "shortSymbol": "KOGE",
      "chainId": "56",
      "fourX": false,
      "change5m": -0.000001163906542583421,
      "volatility5m": 0.000012499443808574047,
      "stability": "稳定",
      "quoteVolume24h": 479648498.5916799,
      "pair": "ALPHA_22USDT",
      "listedDays": 174
    },
    {
      "shortSymbol": "NUMI",
      "chainId": "56",
      "fourX": true,
      "change5m": 0.000002476464915630546,
      "volatility5m": 0.000013372910544588244,
      "stability": "稳定",
      "quoteVolume24h": 309651578.9425115,
      "pair": "ALPHA_387USDT",
      "listedDays": 17
    },
    {
      "shortSymbol": "ALEO",
      "chainId": "56",
      "fourX": true,
      "change5m": 0.00003519078429983554,
      "volatility5m": 0.0012028880058430945,
      "stability": "稳定",
      "quoteVolume24h": 692220986.7642529,
      "pair": "ALPHA_373USDT",
      "listedDays": 24
    },
    {
      "shortSymbol": "ZEUS",
      "chainId": "56",
      "fourX": true,
      "change5m": 0.0004244842516342176,
      "volatility5m": 0.001264283895067466,
      "stability": "稳定",
      "quoteVolume24h": 484314242.49025184,
      "pair": "ALPHA_372USDT",
      "listedDays": 25
    },
    {
      "shortSymbol": "AOP",
      "chainId": "56",
      "fourX": true,
      "change5m": 0.0010880149400041964,
      "volatility5m": 0.0014225271602428932,
      "stability": "稳定",
      "quoteVolume24h": 4049473543.0256686,
      "pair": "ALPHA_382USDT",
      "listedDays": 19
    },
    {
      "shortSymbol": "PINGPONG",
      "chainId": "56",
      "fourX": true,
      "change5m": -0.0013163051300073443,
      "volatility5m": 0.00310583179970541,
      "stability": "稳定",
      "quoteVolume24h": 1369850816.5651503,
      "pair": "ALPHA_368USDT",
      "listedDays": 27
    },
    {
      "shortSymbol": "Q",
      "chainId": "56",
      "fourX": false,
      "change5m": 0.000978673241872046,
      "volatility5m": 0.0054799302664209045,
      "stability": "稳定",
      "quoteVolume24h": 1578976442.4286675,
      "pair": "ALPHA_349USDT",
      "listedDays": 36
    },
    {
      "shortSymbol": "POP",
      "chainId": "56",
      "fourX": true,
      "change5m": -0.008936914543487594,
      "volatility5m": 0.021844001012681368,
      "stability": "稳定",
      "quoteVolume24h": 297014304.40419376,
      "pair": "ALPHA_366USDT",
      "listedDays": 28
    },
    {
      "shortSymbol": "币安人生",
      "chainId": "56",
      "fourX": true,
      "change5m": -0.028995755904661975,
      "volatility5m": 0.0393621773510057,
      "stability": "稳定",
      "quoteVolume24h": 108493100.2595195,
      "pair": "ALPHA_416USDT",
      "listedDays": 1
    }
  ]
}