{
  "updatedAt": "2025-12-30T16:38:39.183Z",
  "rows": [
    {
      "shortSymbol": "LISA",
      "chainId": "56",
      "fourX": true,
      "change5m": 0,
      "volatility5m": 0.001291130952380874,
      "stability": "稳定",
      "quoteVolume24h": 2955483256.2363563,
      "pair": "ALPHA_501USDT",
      "listedDays": 12
    },
    {
      "shortSymbol": "KGEN",
      "chainId": "56",
      "fourX": false,
      "change5m": -0.0000827692307692196,
      "volatility5m": 0.0016267692307692662,
      "stability": "稳定",
      "quoteVolume24h": 479355828.2872239,
      "pair": "ALPHA_414USDT",
      "listedDays": 84
    },
    {
      "shortSymbol": "ESPORTS",
      "chainId": "56",
      "fourX": false,
      "change5m": 0.000029903846872694514,
      "volatility5m": 0.0016913942714277851,
      "stability": "稳定",
      "quoteVolume24h": 236031541.61938864,
      "pair": "ALPHA_283USDT",
      "listedDays": 164
    },
    {
      "shortSymbol": "STABLE",
      "chainId": "56",
      "fourX": true,
      "change5m": -0.0022854290220252196,
      "volatility5m": 0.0037823138226105637,
      "stability": "稳定",
      "quoteVolume24h": 254554734.11801076,
      "pair": "ALPHA_488USDT",
      "listedDays": 22
    },
    {
      "shortSymbol": "RLS",
      "chainId": "56",
      "fourX": true,
      "change5m": -0.007358023688687129,
      "volatility5m": 0.011299664452932894,
      "stability": "稳定",
      "quoteVolume24h": 104198009.54047745,
      "pair": "ALPHA_486USDT",
      "listedDays": 29
    }
  ]
}