{
  "updatedAt": "2025-12-27T19:23:34.267Z",
  "rows": [
    {
      "shortSymbol": "ESPORTS",
      "chainId": "56",
      "fourX": false,
      "change5m": 0.000756775255431689,
      "volatility5m": 0.001347959070022529,
      "stability": "稳定",
      "quoteVolume24h": 712781055.3457103,
      "pair": "ALPHA_283USDT",
      "listedDays": 161
    },
    {
      "shortSymbol": "KGEN",
      "chainId": "56",
      "fourX": false,
      "change5m": 0.0015918743768694244,
      "volatility5m": 0.0028974576271187233,
      "stability": "稳定",
      "quoteVolume24h": 489077745.1070039,
      "pair": "ALPHA_414USDT",
      "listedDays": 81
    },
    {
      "shortSymbol": "LISA",
      "chainId": "56",
      "fourX": true,
      "change5m": 5.866823456391192e-8,
      "volatility5m": 0.0029500735083645615,
      "stability": "稳定",
      "quoteVolume24h": 2076394255.1754427,
      "pair": "ALPHA_501USDT",
      "listedDays": 9
    },
    {
      "shortSymbol": "RLS",
      "chainId": "56",
      "fourX": true,
      "change5m": -0.0038979594029061606,
      "volatility5m": 0.006828334788673865,
      "stability": "稳定",
      "quoteVolume24h": 508961318.2955931,
      "pair": "ALPHA_486USDT",
      "listedDays": 26
    },
    {
      "shortSymbol": "STABLE",
      "chainId": "56",
      "fourX": true,
      "change5m": 0.0008442420222803258,
      "volatility5m": 0.012186072544701677,
      "stability": "稳定",
      "quoteVolume24h": 200557745.84212145,
      "pair": "ALPHA_488USDT",
      "listedDays": 19
    }
  ]
}