{
  "updatedAt": "2026-03-24T19:17:59.956Z",
  "rows": [
    {
      "shortSymbol": "BSB",
      "chainId": "56",
      "fourX": true,
      "change5m": -0.0008745391673028446,
      "volatility5m": 0.0013597075392692683,
      "stability": "稳定",
      "quoteVolume24h": 288507901.3414786,
      "pair": "ALPHA_790USDT",
      "listedDays": 20
    },
    {
      "shortSymbol": "UP",
      "chainId": "56",
      "fourX": true,
      "change5m": -0.0002555618703208984,
      "volatility5m": 0.002180860467093259,
      "stability": "稳定",
      "quoteVolume24h": 119022900.34852532,
      "pair": "ALPHA_804USDT",
      "listedDays": 11
    },
    {
      "shortSymbol": "GUA",
      "chainId": "56",
      "fourX": false,
      "change5m": -0.003196535983485165,
      "volatility5m": 0.004124248233612526,
      "stability": "稳定",
      "quoteVolume24h": 1192973336.7470982,
      "pair": "ALPHA_483USDT",
      "listedDays": 117
    }
  ]
}