{
  "updatedAt": "2026-02-18T10:03:13.260Z",
  "rows": [
    {
      "shortSymbol": "BSU",
      "chainId": "56",
      "fourX": false,
      "change5m": 0,
      "volatility5m": 0,
      "stability": "稳定",
      "quoteVolume24h": 147147039.14547643,
      "pair": "ALPHA_315USDT",
      "listedDays": 193
    },
    {
      "shortSymbol": "WMTX",
      "chainId": "56",
      "fourX": true,
      "change5m": 0.00032134870983137695,
      "volatility5m": 0.00047046556619190856,
      "stability": "稳定",
      "quoteVolume24h": 1728739671.2157552,
      "pair": "ALPHA_611USDT",
      "listedDays": 23
    },
    {
      "shortSymbol": "GWEI",
      "chainId": "56",
      "fourX": true,
      "change5m": 0.0017359809687115823,
      "volatility5m": 0.0042564482157121135,
      "stability": "稳定",
      "quoteVolume24h": 123069596.88145466,
      "pair": "ALPHA_588USDT",
      "listedDays": 28
    },
    {
      "shortSymbol": "MERL",
      "chainId": "56",
      "fourX": false,
      "change5m": 0.0016633060434532183,
      "volatility5m": 0.0053726242823247785,
      "stability": "稳定",
      "quoteVolume24h": 227277470.16758966,
      "pair": "ALPHA_195USDT",
      "listedDays": 274
    },
    {
      "shortSymbol": "ARTX",
      "chainId": "56",
      "fourX": false,
      "change5m": -0.0008182398207711058,
      "volatility5m": 0.006868118071942978,
      "stability": "稳定",
      "quoteVolume24h": 92717520.3693245,
      "pair": "ALPHA_474USDT",
      "listedDays": 89
    },
    {
      "shortSymbol": "COLLECT",
      "chainId": "56",
      "fourX": false,
      "change5m": 0.0033330280630600216,
      "volatility5m": 0.008107411526133214,
      "stability": "稳定",
      "quoteVolume24h": 267009678.39169985,
      "pair": "ALPHA_506USDT",
      "listedDays": 53
    }
  ]
}