{
  "updatedAt": "2026-03-19T09:57:51.232Z",
  "rows": [
    {
      "shortSymbol": "GUA",
      "chainId": "56",
      "fourX": false,
      "change5m": -0.00001769911504415521,
      "volatility5m": 0.0010836192884234152,
      "stability": "稳定",
      "quoteVolume24h": 1161327043.3098726,
      "pair": "ALPHA_483USDT",
      "listedDays": 112
    },
    {
      "shortSymbol": "VELVET",
      "chainId": "56",
      "fourX": false,
      "change5m": -0.0007200891600404262,
      "volatility5m": 0.0018799984565974549,
      "stability": "稳定",
      "quoteVolume24h": 126694932.69160028,
      "pair": "ALPHA_267USDT",
      "listedDays": 252
    },
    {
      "shortSymbol": "H",
      "chainId": "56",
      "fourX": false,
      "change5m": -0.0004878537953598972,
      "volatility5m": 0.0019190831920561703,
      "stability": "稳定",
      "quoteVolume24h": 141355399.8296793,
      "pair": "ALPHA_245USDT",
      "listedDays": 267
    },
    {
      "shortSymbol": "TRIA",
      "chainId": "56",
      "fourX": false,
      "change5m": 0.0010479843316043144,
      "volatility5m": 0.0050148879485974705,
      "stability": "稳定",
      "quoteVolume24h": 195446613.94579068,
      "pair": "ALPHA_669USDT",
      "listedDays": 44
    }
  ]
}