{
  "updatedAt": "2026-03-01T09:47:58.404Z",
  "rows": [
    {
      "shortSymbol": "STABLE",
      "chainId": "56",
      "fourX": false,
      "change5m": -0.0006046583801143773,
      "volatility5m": 0.003039928324237135,
      "stability": "稳定",
      "quoteVolume24h": 1659124786.1610918,
      "pair": "ALPHA_488USDT",
      "listedDays": 83
    },
    {
      "shortSymbol": "JCT",
      "chainId": "56",
      "fourX": false,
      "change5m": 0.0020586098328893936,
      "volatility5m": 0.0032568099833016856,
      "stability": "稳定",
      "quoteVolume24h": 97364688.00411533,
      "pair": "ALPHA_466USDT",
      "listedDays": 111
    },
    {
      "shortSymbol": "GUA",
      "chainId": "56",
      "fourX": false,
      "change5m": -0.002459689578714024,
      "volatility5m": 0.003985631929046557,
      "stability": "稳定",
      "quoteVolume24h": 152979388.9617269,
      "pair": "ALPHA_483USDT",
      "listedDays": 94
    }
  ]
}