{
  "updatedAt": "2025-12-29T20:42:07.604Z",
  "rows": [
    {
      "shortSymbol": "LISA",
      "chainId": "56",
      "fourX": true,
      "change5m": 0,
      "volatility5m": 0.00026489715445965323,
      "stability": "稳定",
      "quoteVolume24h": 1991329617.4665942,
      "pair": "ALPHA_501USDT",
      "listedDays": 11
    },
    {
      "shortSymbol": "ESPORTS",
      "chainId": "56",
      "fourX": false,
      "change5m": 0.00003367680115610844,
      "volatility5m": 0.0007082081977106746,
      "stability": "稳定",
      "quoteVolume24h": 845894303.3904157,
      "pair": "ALPHA_283USDT",
      "listedDays": 163
    },
    {
      "shortSymbol": "KGEN",
      "chainId": "56",
      "fourX": false,
      "change5m": 0.0007604739113778152,
      "volatility5m": 0.0008707995674314476,
      "stability": "稳定",
      "quoteVolume24h": 554765191.9741566,
      "pair": "ALPHA_414USDT",
      "listedDays": 83
    },
    {
      "shortSymbol": "STABLE",
      "chainId": "56",
      "fourX": true,
      "change5m": -0.001202792064658334,
      "volatility5m": 0.0018038207200587744,
      "stability": "稳定",
      "quoteVolume24h": 250526982.40878576,
      "pair": "ALPHA_488USDT",
      "listedDays": 21
    },
    {
      "shortSymbol": "RLS",
      "chainId": "56",
      "fourX": true,
      "change5m": -0.0006934743831174473,
      "volatility5m": 0.002474946613176649,
      "stability": "稳定",
      "quoteVolume24h": 396678231.8684823,
      "pair": "ALPHA_486USDT",
      "listedDays": 28
    }
  ]
}