{
  "updatedAt": "2025-12-30T19:45:19.711Z",
  "rows": [
    {
      "shortSymbol": "STABLE",
      "chainId": "56",
      "fourX": true,
      "change5m": 0,
      "volatility5m": 0.00010792452830190047,
      "stability": "稳定",
      "quoteVolume24h": 255363591.48443228,
      "pair": "ALPHA_488USDT",
      "listedDays": 22
    },
    {
      "shortSymbol": "LISA",
      "chainId": "56",
      "fourX": true,
      "change5m": -0.0000010119037379175642,
      "volatility5m": 0.00020714264753423462,
      "stability": "稳定",
      "quoteVolume24h": 2959133657.3160295,
      "pair": "ALPHA_501USDT",
      "listedDays": 12
    },
    {
      "shortSymbol": "KGEN",
      "chainId": "56",
      "fourX": false,
      "change5m": -0.00023451660986274019,
      "volatility5m": 0.00023451660986274019,
      "stability": "稳定",
      "quoteVolume24h": 479850638.8924318,
      "pair": "ALPHA_414USDT",
      "listedDays": 84
    },
    {
      "shortSymbol": "ESPORTS",
      "chainId": "56",
      "fourX": false,
      "change5m": 0.00038438617049108427,
      "volatility5m": 0.001175349031649344,
      "stability": "稳定",
      "quoteVolume24h": 237429655.56976163,
      "pair": "ALPHA_283USDT",
      "listedDays": 164
    },
    {
      "shortSymbol": "RLS",
      "chainId": "56",
      "fourX": true,
      "change5m": 0.0008384604353130778,
      "volatility5m": 0.0011789475165997114,
      "stability": "稳定",
      "quoteVolume24h": 97469781.29347628,
      "pair": "ALPHA_486USDT",
      "listedDays": 29
    }
  ]
}