{
  "updatedAt": "2026-02-14T19:41:36.948Z",
  "rows": [
    {
      "shortSymbol": "ARTX",
      "chainId": "56",
      "fourX": false,
      "change5m": -3.92156862538684e-8,
      "volatility5m": 3.92156862538684e-8,
      "stability": "稳定",
      "quoteVolume24h": 215441515.26306647,
      "pair": "ALPHA_474USDT",
      "listedDays": 85
    },
    {
      "shortSymbol": "WMTX",
      "chainId": "56",
      "fourX": true,
      "change5m": -0.0003833873484574985,
      "volatility5m": 0.0011999759932781752,
      "stability": "稳定",
      "quoteVolume24h": 1745538362.8847332,
      "pair": "ALPHA_611USDT",
      "listedDays": 19
    },
    {
      "shortSymbol": "GWEI",
      "chainId": "56",
      "fourX": true,
      "change5m": -0.0007270465672238575,
      "volatility5m": 0.002974874488421683,
      "stability": "稳定",
      "quoteVolume24h": 65485278.21076614,
      "pair": "ALPHA_588USDT",
      "listedDays": 24
    },
    {
      "shortSymbol": "FIGHT",
      "chainId": "56",
      "fourX": true,
      "change5m": -0.00197433662890285,
      "volatility5m": 0.0031823782191904297,
      "stability": "稳定",
      "quoteVolume24h": 201944770.3055566,
      "pair": "ALPHA_604USDT",
      "listedDays": 23
    }
  ]
}