{
  "updatedAt": "2026-04-10T15:34:15.352Z",
  "rows": [
    {
      "shortSymbol": "EDGE",
      "chainId": "56",
      "fourX": true,
      "change5m": -0.0005039399279910282,
      "volatility5m": 0.0027401586253133145,
      "stability": "稳定",
      "quoteVolume24h": 70403668.1027704,
      "pair": "ALPHA_838USDT",
      "listedDays": 10
    },
    {
      "shortSymbol": "PRL",
      "chainId": "56",
      "fourX": true,
      "change5m": -0.0025612578841810135,
      "volatility5m": 0.009235794567834079,
      "stability": "稳定",
      "quoteVolume24h": 153487647.80131304,
      "pair": "ALPHA_823USDT",
      "listedDays": 16
    },
    {
      "shortSymbol": "BEAT",
      "chainId": "56",
      "fourX": false,
      "change5m": -0.00857364654032244,
      "volatility5m": 0.014652473277552468,
      "stability": "稳定",
      "quoteVolume24h": 244957668.3434133,
      "pair": "ALPHA_451USDT",
      "listedDays": 160
    },
    {
      "shortSymbol": "UP",
      "chainId": "56",
      "fourX": true,
      "change5m": 0.0184688908525941,
      "volatility5m": 0.04247338701733995,
      "stability": "稳定",
      "quoteVolume24h": 918539952.3339989,
      "pair": "ALPHA_804USDT",
      "listedDays": 28
    }
  ]
}