{
  "updatedAt": "2025-11-22T07:24:53.820Z",
  "rows": [
    {
      "shortSymbol": "KOGE",
      "chainId": "56",
      "fourX": false,
      "change5m": 2.2498852226671732e-8,
      "volatility5m": 2.354046554187449e-8,
      "stability": "稳定",
      "quoteVolume24h": 201038242.73017284,
      "pair": "ALPHA_22USDT",
      "listedDays": 219
    },
    {
      "shortSymbol": "AIO",
      "chainId": "56",
      "fourX": false,
      "change5m": 0.000010384928087818793,
      "volatility5m": 0.00004274127427875301,
      "stability": "稳定",
      "quoteVolume24h": 4076394077.308423,
      "pair": "ALPHA_361USDT",
      "listedDays": 75
    },
    {
      "shortSymbol": "TIMI",
      "chainId": "56",
      "fourX": true,
      "change5m": -0.0019096633139829677,
      "volatility5m": 0.002194009387105264,
      "stability": "稳定",
      "quoteVolume24h": 145362584.06286085,
      "pair": "ALPHA_465USDT",
      "listedDays": 13
    },
    {
      "shortSymbol": "AT",
      "chainId": "56",
      "fourX": true,
      "change5m": 0.0016570334165656288,
      "volatility5m": 0.002617830641262557,
      "stability": "稳定",
      "quoteVolume24h": 539517374.4538616,
      "pair": "ALPHA_443USDT",
      "listedDays": 29
    },
    {
      "shortSymbol": "BOS",
      "chainId": "56",
      "fourX": true,
      "change5m": -0.0015248297879525026,
      "volatility5m": 0.002969131938040531,
      "stability": "稳定",
      "quoteVolume24h": 177604324.32379228,
      "pair": "ALPHA_449USDT",
      "listedDays": 24
    },
    {
      "shortSymbol": "BAY",
      "chainId": "56",
      "fourX": true,
      "change5m": 0.005564994181373256,
      "volatility5m": 0.007586077859060654,
      "stability": "稳定",
      "quoteVolume24h": 155650849.2572319,
      "pair": "ALPHA_452USDT",
      "listedDays": 21
    },
    {
      "shortSymbol": "COMMON",
      "chainId": "56",
      "fourX": true,
      "change5m": 0.009114951985370816,
      "volatility5m": 0.015418641600687509,
      "stability": "稳定",
      "quoteVolume24h": 81817366.46960516,
      "pair": "ALPHA_447USDT",
      "listedDays": 26
    }
  ]
}